auto/__init__.py
auto/cli.py
caki-0.8.1.dist-info/METADATA
caki-0.8.1.dist-info/WHEEL
caki-0.8.1.dist-info/entry_points.txt
caki-0.8.1.dist-info/top_level.txt
caki-0.8.1.dist-info/RECORD
