Metadata-Version: 2.4
Name: caki
Version: 0.8.1
Summary: Auto-installer CLI wrapper for pip packages
Author: Mufaddal Jawadwala
Classifier: Programming Language :: Python :: 3
Classifier: License :: OSI Approved :: MIT License
Classifier: Operating System :: OS Independent
Requires-Python: >=3.6
Dynamic: author
Dynamic: classifier
Dynamic: description
Dynamic: description-content-type
Dynamic: requires-python
Dynamic: summary
